{
    "coordinates": {
        "x": 0.15766233766233767,
        "y": 0.3098909364422715
    },
    "measure": [
        {
            "bssid": "64f69db3ed35",
            "rssi": -79.16666666666667
        },
        {
            "bssid": "64f69db3ed30",
            "rssi": -78.33333333333333
        },
        {
            "bssid": "64f69db3ed34",
            "rssi": -79.11111111111111
        },
        {
            "bssid": "64f69db3ed32",
            "rssi": -78.75
        },
        {
            "bssid": "64f69db3ed33",
            "rssi": -79.0
        },
        {
            "bssid": "64f69db3ed31",
            "rssi": -79.0
        },
        {
            "bssid": "488b0a1a2fc0",
            "rssi": -84.0
        },
        {
            "bssid": "488b0a1a2fc1",
            "rssi": -84.33333333333333
        },
        {
            "bssid": "488b0a1a2fc2",
            "rssi": -84.14285714285714
        },
        {
            "bssid": "488b0a1a2fc3",
            "rssi": -84.88888888888889
        },
        {
            "bssid": "488b0a1a2fc4",
            "rssi": -83.75
        },
        {
            "bssid": "488b0a1a2fc5",
            "rssi": -84.55555555555556
        },
        {
            "bssid": "a0239f9ed713",
            "rssi": -83.0
        },
        {
            "bssid": "a0239f9ed710",
            "rssi": -84.25
        },
        {
            "bssid": "a0239f9ed714",
            "rssi": -85.0
        },
        {
            "bssid": "a0239f9ed712",
            "rssi": -85.0
        },
        {
            "bssid": "a0239f9ed715",
            "rssi": -86.0
        },
        {
            "bssid": "d8b190c32c44",
            "rssi": -84.5
        },
        {
            "bssid": "a0239f9ed711",
            "rssi": -86.25
        },
        {
            "bssid": "d8b190c32c43",
            "rssi": -85.33333333333333
        },
        {
            "bssid": "d8b190c32c40",
            "rssi": -85.25
        },
        {
            "bssid": "d8b190c32c45",
            "rssi": -87.0
        },
        {
            "bssid": "d8b190c32c41",
            "rssi": -86.0
        },
        {
            "bssid": "d8b190c32c42",
            "rssi": -86.25
        }
    ]
}