{
    "coordinates": {
        "x": 0.4878288507461548,
        "y": 0.7044022083282471
    },
    "measurements": [
        {
            "bssid": "6afa52bc9ff2",
            "rssi": -91
        },
        {
            "bssid": "64f69db3ed3c",
            "rssi": -77
        },
        {
            "bssid": "488b0a1a9aea",
            "rssi": -81
        },
        {
            "bssid": "64f69db3ed3b",
            "rssi": -77
        },
        {
            "bssid": "488b0a1a9aec",
            "rssi": -82
        },
        {
            "bssid": "64f69db3ed3d",
            "rssi": -77
        },
        {
            "bssid": "488b0a1a9aeb",
            "rssi": -81
        },
        {
            "bssid": "64f69db3ed3f",
            "rssi": -76
        },
        {
            "bssid": "488b0a1a9aed",
            "rssi": -81
        },
        {
            "bssid": "a89d214422c4",
            "rssi": -70
        },
        {
            "bssid": "d8b190c32c40",
            "rssi": -74
        },
        {
            "bssid": "488b0a1a9aef",
            "rssi": -82
        },
        {
            "bssid": "a89d217468bf",
            "rssi": -83
        },
        {
            "bssid": "64f69d4df820",
            "rssi": -88
        },
        {
            "bssid": "d8b190c32c42",
            "rssi": -75
        },
        {
            "bssid": "a89d217468bd",
            "rssi": -83
        },
        {
            "bssid": "d8b190c32c43",
            "rssi": -74
        },
        {
            "bssid": "a89d217468bc",
            "rssi": -83
        },
        {
            "bssid": "d8b190c32c45",
            "rssi": -77
        },
        {
            "bssid": "a89d217468ba",
            "rssi": -84
        },
        {
            "bssid": "d8b1906ee905",
            "rssi": -82
        },
        {
            "bssid": "8283c241e684",
            "rssi": -93
        },
        {
            "bssid": "d8b1906ee903",
            "rssi": -82
        },
        {
            "bssid": "488b0a1a9ae0",
            "rssi": -81
        },
        {
            "bssid": "d8b1906ee904",
            "rssi": -81
        },
        {
            "bssid": "488b0a1a9ae3",
            "rssi": -81
        },
        {
            "bssid": "d8b1906ee902",
            "rssi": -81
        },
        {
            "bssid": "488b0a1a9ae2",
            "rssi": -82
        },
        {
            "bssid": "488b0a1a9ae4",
            "rssi": -83
        },
        {
            "bssid": "d8b1906ee900",
            "rssi": -84
        },
        {
            "bssid": "a89d214422cd",
            "rssi": -77
        },
        {
            "bssid": "a89d214422cf",
            "rssi": -77
        },
        {
            "bssid": "a89d214422cb",
            "rssi": -77
        },
        {
            "bssid": "a89d214422cc",
            "rssi": -78
        },
        {
            "bssid": "a0239f9ed71f",
            "rssi": -81
        },
        {
            "bssid": "a0239f9ed71c",
            "rssi": -82
        },
        {
            "bssid": "5488deb1ee2d",
            "rssi": -71
        },
        {
            "bssid": "64f69db3ed30",
            "rssi": -71
        },
        {
            "bssid": "5488deb1ee2c",
            "rssi": -71
        },
        {
            "bssid": "64f69db3ed33",
            "rssi": -71
        },
        {
            "bssid": "5488deb1ee2b",
            "rssi": -71
        },
        {
            "bssid": "64f69db3ed32",
            "rssi": -72
        },
        {
            "bssid": "64f69db3ed35",
            "rssi": -71
        },
        {
            "bssid": "64f69db3ed34",
            "rssi": -72
        },
        {
            "bssid": "5488deb1ee2f",
            "rssi": -64
        },
        {
            "bssid": "d8b190c32c4a",
            "rssi": -68
        },
        {
            "bssid": "a89d217468b5",
            "rssi": -76
        },
        {
            "bssid": "d8b190c32c4c",
            "rssi": -69
        },
        {
            "bssid": "a89d217468b3",
            "rssi": -76
        },
        {
            "bssid": "d8b190c32c4d",
            "rssi": -69
        },
        {
            "bssid": "a89d217468b2",
            "rssi": -76
        },
        {
            "bssid": "d8b190c32c4e",
            "rssi": -68
        },
        {
            "bssid": "d8b190c32c4f",
            "rssi": -69
        },
        {
            "bssid": "a89d217468b0",
            "rssi": -76
        },
        {
            "bssid": "70df2f14027f",
            "rssi": -82
        },
        {
            "bssid": "70df2f14027c",
            "rssi": -82
        },
        {
            "bssid": "70df2f14027b",
            "rssi": -81
        },
        {
            "bssid": "70df2f14027a",
            "rssi": -81
        },
        {
            "bssid": "a89d214422c0",
            "rssi": -71
        },
        {
            "bssid": "a89d214422c2",
            "rssi": -70
        },
        {
            "bssid": "a89d214422c3",
            "rssi": -70
        },
        {
            "bssid": "70df2f140275",
            "rssi": -79
        },
        {
            "bssid": "70df2f140274",
            "rssi": -79
        },
        {
            "bssid": "70df2f140273",
            "rssi": -79
        },
        {
            "bssid": "70df2f140272",
            "rssi": -79
        },
        {
            "bssid": "70df2f140270",
            "rssi": -79
        },
        {
            "bssid": "5488deb1ee24",
            "rssi": -75
        },
        {
            "bssid": "5488deb1ee23",
            "rssi": -75
        },
        {
            "bssid": "5488deb1ee22",
            "rssi": -75
        },
        {
            "bssid": "5488deb1ee25",
            "rssi": -75
        },
        {
            "bssid": "5488deb1ee20",
            "rssi": -75
        }
    ]
}