{
    "coordinates": {
        "x": 0.8733309507369995,
        "y": 0.7503986954689026
    },
    "measurements": [
        {
            "bssid": "cc46d6da81fc",
            "rssi": -58
        },
        {
            "bssid": "f01d2d8cd2e0",
            "rssi": -80
        },
        {
            "bssid": "cc46d6da81fb",
            "rssi": -58
        },
        {
            "bssid": "a89d216db0fb",
            "rssi": -66
        },
        {
            "bssid": "f01d2d8cd2e2",
            "rssi": -80
        },
        {
            "bssid": "a89d216db0fd",
            "rssi": -66
        },
        {
            "bssid": "f01d2d8cd2e4",
            "rssi": -81
        },
        {
            "bssid": "cc46d6da81ff",
            "rssi": -58
        },
        {
            "bssid": "a89d216db0fc",
            "rssi": -68
        },
        {
            "bssid": "cc46d6da81fe",
            "rssi": -58
        },
        {
            "bssid": "a89d216db0ff",
            "rssi": -67
        },
        {
            "bssid": "cc46d6da81fd",
            "rssi": -58
        },
        {
            "bssid": "a89d216db0fe",
            "rssi": -68
        },
        {
            "bssid": "cc46d6da81f3",
            "rssi": -57
        },
        {
            "bssid": "a89d216db0f0",
            "rssi": -68
        },
        {
            "bssid": "cc46d6da81f2",
            "rssi": -56
        },
        {
            "bssid": "a89d216db0f2",
            "rssi": -68
        },
        {
            "bssid": "f01d2d8cd2ea",
            "rssi": -82
        },
        {
            "bssid": "cc46d6da81f0",
            "rssi": -57
        },
        {
            "bssid": "a89d216db0f1",
            "rssi": -69
        },
        {
            "bssid": "f01d2d8cd2eb",
            "rssi": -83
        },
        {
            "bssid": "a89d216db0f4",
            "rssi": -68
        },
        {
            "bssid": "f01d2d8cd2ec",
            "rssi": -83
        },
        {
            "bssid": "a89d216db0f3",
            "rssi": -68
        },
        {
            "bssid": "f01d2d8cd2ed",
            "rssi": -83
        },
        {
            "bssid": "cc46d6da81f5",
            "rssi": -56
        },
        {
            "bssid": "f01d2d8cd2ee",
            "rssi": -81
        },
        {
            "bssid": "cc46d6da81f4",
            "rssi": -56
        },
        {
            "bssid": "f01d2d8cd2ef",
            "rssi": -82
        },
        {
            "bssid": "ee35611e30a5",
            "rssi": -80
        },
        {
            "bssid": "70df2f2c1194",
            "rssi": -82
        },
        {
            "bssid": "70df2f2c1192",
            "rssi": -82
        },
        {
            "bssid": "70df2f2c1190",
            "rssi": -82
        }
    ]
}