{
    "coordinates": {
        "x": 0.560340940952301,
        "y": 0.6912704110145569
    },
    "measurements": [
        {
            "bssid": "64f69db3ed3a",
            "rssi": -78
        },
        {
            "bssid": "488b0a1a9aea",
            "rssi": -77
        },
        {
            "bssid": "64f69db3ed3c",
            "rssi": -77
        },
        {
            "bssid": "64f69db3ed3b",
            "rssi": -77
        },
        {
            "bssid": "488b0a1a9aec",
            "rssi": -79
        },
        {
            "bssid": "64f69db3ed3d",
            "rssi": -77
        },
        {
            "bssid": "488b0a1a9aeb",
            "rssi": -89
        },
        {
            "bssid": "488b0a1a9aee",
            "rssi": -77
        },
        {
            "bssid": "a89d216db0f5",
            "rssi": -86
        },
        {
            "bssid": "488b0a1a9aed",
            "rssi": -90
        },
        {
            "bssid": "d8b190c32c40",
            "rssi": -70
        },
        {
            "bssid": "488b0a1a9aef",
            "rssi": -77
        },
        {
            "bssid": "d8b190c32c41",
            "rssi": -70
        },
        {
            "bssid": "d8b190c32c42",
            "rssi": -70
        },
        {
            "bssid": "d8b190c32c43",
            "rssi": -71
        },
        {
            "bssid": "d8b190c32c44",
            "rssi": -70
        },
        {
            "bssid": "d8b190c32c45",
            "rssi": -70
        },
        {
            "bssid": "488b0a1a9ae0",
            "rssi": -69
        },
        {
            "bssid": "d8b1906ee901",
            "rssi": -87
        },
        {
            "bssid": "488b0a1a9ae2",
            "rssi": -69
        },
        {
            "bssid": "d8b1906ee902",
            "rssi": -88
        },
        {
            "bssid": "488b0a1a9ae5",
            "rssi": -69
        },
        {
            "bssid": "5488deb1ee2d",
            "rssi": -68
        },
        {
            "bssid": "64f69db3ed31",
            "rssi": -73
        },
        {
            "bssid": "5488deb1ee2c",
            "rssi": -68
        },
        {
            "bssid": "64f69db3ed30",
            "rssi": -73
        },
        {
            "bssid": "5488deb1ee2b",
            "rssi": -68
        },
        {
            "bssid": "5488deb1ee2a",
            "rssi": -68
        },
        {
            "bssid": "64f69db3ed32",
            "rssi": -74
        },
        {
            "bssid": "64f69db3ed34",
            "rssi": -73
        },
        {
            "bssid": "5488deb1ee2f",
            "rssi": -68
        },
        {
            "bssid": "5488deb1ee2e",
            "rssi": -69
        },
        {
            "bssid": "64f69d4df824",
            "rssi": -80
        },
        {
            "bssid": "64f69d4df823",
            "rssi": -81
        },
        {
            "bssid": "5488deb1ee24",
            "rssi": -67
        },
        {
            "bssid": "5488deb1ee23",
            "rssi": -67
        },
        {
            "bssid": "5488deb1ee22",
            "rssi": -66
        },
        {
            "bssid": "5488deb1ee21",
            "rssi": -67
        },
        {
            "bssid": "5488deb1ee20",
            "rssi": -67
        },
        {
            "bssid": "548aba1d5280",
            "rssi": -83
        },
        {
            "bssid": "548aba1d5282",
            "rssi": -83
        },
        {
            "bssid": "64f69d4df822",
            "rssi": -80
        },
        {
            "bssid": "64f69d4df820",
            "rssi": -81
        },
        {
            "bssid": "64f69d4afb74",
            "rssi": -90
        },
        {
            "bssid": "64f69d4afb73",
            "rssi": -90
        },
        {
            "bssid": "64f69d4afb71",
            "rssi": -89
        },
        {
            "bssid": "64f69d4afb70",
            "rssi": -89
        },
        {
            "bssid": "a0239f9ed71f",
            "rssi": -83
        },
        {
            "bssid": "a0239f9ed71c",
            "rssi": -84
        },
        {
            "bssid": "d8b190c32c4a",
            "rssi": -62
        },
        {
            "bssid": "d8b190c32c4b",
            "rssi": -63
        },
        {
            "bssid": "a89d217468b4",
            "rssi": -87
        },
        {
            "bssid": "d8b190c32c4c",
            "rssi": -62
        },
        {
            "bssid": "d8b190c32c4d",
            "rssi": -62
        },
        {
            "bssid": "a89d217468b2",
            "rssi": -87
        },
        {
            "bssid": "d8b190c32c4f",
            "rssi": -62
        },
        {
            "bssid": "84b80204a595",
            "rssi": -82
        },
        {
            "bssid": "84b80204a594",
            "rssi": -82
        },
        {
            "bssid": "84b80204a593",
            "rssi": -82
        },
        {
            "bssid": "84b80204a592",
            "rssi": -82
        },
        {
            "bssid": "84b80204a591",
            "rssi": -81
        },
        {
            "bssid": "84b80204a590",
            "rssi": -82
        },
        {
            "bssid": "70df2f14027f",
            "rssi": -76
        },
        {
            "bssid": "70df2f14027e",
            "rssi": -75
        },
        {
            "bssid": "70df2f14027d",
            "rssi": -76
        },
        {
            "bssid": "70df2f14027c",
            "rssi": -76
        },
        {
            "bssid": "70df2f14027a",
            "rssi": -76
        },
        {
            "bssid": "e4fac449152b",
            "rssi": -88
        },
        {
            "bssid": "70df2f140274",
            "rssi": -74
        },
        {
            "bssid": "70df2f140273",
            "rssi": -74
        },
        {
            "bssid": "70df2f140272",
            "rssi": -73
        },
        {
            "bssid": "70df2f140271",
            "rssi": -74
        },
        {
            "bssid": "70df2f140270",
            "rssi": -75
        }
    ]
}